{
    "common": {
        "name":                     "socketio",
        "version":                  "0.0.0",
        "title":                    "Socket.io Adapter",
        "desc":                     "provides a pure Socket.io server without webserver",
        "platform":                 "javascript/Node.js",
        "mode":                     "daemon",
        "noRepository":             true,
        "loglevel":                 "info"
    },
    "native": {
        "listenPort":               8080,
        "listenPortSsl":            null,
        "auth":                     false,
        "authSsl":                  false
    },
    "objects": [

    ]
}